pycksum/__init__.py
pycksum/_pycksum.cpython-39-darwin.so
pycksum/main.py
pycksum-0.5.0.dist-info/licenses/LICENSE
pycksum-0.5.0.dist-info/METADATA
pycksum-0.5.0.dist-info/WHEEL
pycksum-0.5.0.dist-info/entry_points.txt
pycksum-0.5.0.dist-info/top_level.txt
pycksum-0.5.0.dist-info/RECORD
